<?xml version="1.0" encoding="UTF-8"?>


<!DOCTYPE tiles-definitions PUBLIC
       "-//Apache Software Foundation//DTD Tiles Configuration 2.0//EN"
       "http://tiles.apache.org/dtds/tiles-config_2_0.dtd">

<tiles-definitions>

<definition extends="master.page" name="client/list">
<put-attribute name="title" value="Lista de Clientes"/>
<put-attribute name="body" value="/views/client/list.jsp"/>
</definition>

<definition extends="master.page" name="client/edit">
<put-attribute name="title" value="Editar Cliente"/>
<put-attribute name="body" value="/views/client/edit.jsp"/>
</definition>


</tiles-definitions>